appier/__init__.py
appier/amqp.py
appier/amqp.pyi
appier/api.py
appier/api.pyi
appier/asgi.py
appier/asgi.pyi
appier/async_neo.py
appier/async_old.py
appier/asynchronous.py
appier/asynchronous.pyi
appier/base.py
appier/base.pyi
appier/bus.py
appier/bus.pyi
appier/cache.py
appier/cache.pyi
appier/common.py
appier/component.py
appier/component.pyi
appier/compress.py
appier/config.py
appier/controller.py
appier/crypt.py
appier/data.py
appier/data.pyi
appier/defines.py
appier/exceptions.py
appier/execution.py
appier/export.py
appier/extra.py
appier/extra_neo.py
appier/extra_old.py
appier/geo.py
appier/git.py
appier/graph.py
appier/http.py
appier/legacy.py
appier/log.py
appier/meta.py
appier/mock.py
appier/model.py
appier/model.pyi
appier/model_a.py
appier/mongo.py
appier/observer.py
appier/part.py
appier/part.pyi
appier/preferences.py
appier/preferences.pyi
appier/queuing.py
appier/redisdb.py
appier/request.py
appier/scheduler.py
appier/scheduler.pyi
appier/serialize.py
appier/session.py
appier/session.pyi
appier/settings.py
appier/smtp.py
appier/storage.py
appier/storage.pyi
appier/structures.py
appier/typesf.py
appier/typesf.pyi
appier/util.py
appier/validation.py
appier/res/static/css/base.css
appier/res/static/images/favicon.ico
appier/res/static/js/base.js
appier/res/templates/error.html.tpl
appier/res/templates/holder.html.tpl
appier/res/templates/layout.html.tpl
appier/test/__init__.py
appier/test/base.py
appier/test/cache.py
appier/test/config.py
appier/test/crypt.py
appier/test/data.py
appier/test/error_handler.py
appier/test/exception_handler.py
appier/test/exceptions.py
appier/test/export.py
appier/test/graph.py
appier/test/http.py
appier/test/legacy.py
appier/test/log.py
appier/test/mock.py
appier/test/model.py
appier/test/part.py
appier/test/preferences.py
appier/test/queuing.py
appier/test/request.py
appier/test/scheduler.py
appier/test/serialize.py
appier/test/session.py
appier/test/smtp.py
appier/test/storage.py
appier/test/structures.py
appier-1.35.0.dist-info/LICENSE
appier-1.35.0.dist-info/METADATA
appier-1.35.0.dist-info/WHEEL
appier-1.35.0.dist-info/top_level.txt
appier-1.35.0.dist-info/RECORD
